[{"id":"9107112001","district_id":"910711","name":"GUBUGANI"},{"id":"9107112003","district_id":"910711","name":"AMBOK"},{"id":"9107112004","district_id":"910711","name":"AWIYAM"},{"id":"9107112005","district_id":"910711","name":"TUBUGIME"},{"id":"9107112006","district_id":"910711","name":"WARIRU"},{"id":"9107112007","district_id":"910711","name":"DIGI"},{"id":"9107112008","district_id":"910711","name":"KIKUP"},{"id":"9107112009","district_id":"910711","name":"GUNUNG TAYOK"},{"id":"9107112011","district_id":"910711","name":"NAMBU"},{"id":"9107112012","district_id":"910711","name":"ASUA"},{"id":"9107112013","district_id":"910711","name":"DEGEI"},{"id":"9107112014","district_id":"910711","name":"SIGOU"},{"id":"9107112015","district_id":"910711","name":"NALU"}]