[{"id":"9117092001","district_id":"911709","name":"KABE"},{"id":"9117092002","district_id":"911709","name":"KAUMI"},{"id":"9117092003","district_id":"911709","name":"KAYAGAI"},{"id":"9117092004","district_id":"911709","name":"ATI"},{"id":"9117092005","district_id":"911709","name":"UPIN"},{"id":"9117092006","district_id":"911709","name":"TARAGAI"},{"id":"9117092007","district_id":"911709","name":"SENE"},{"id":"9117092008","district_id":"911709","name":"KOMRU"},{"id":"9117092009","district_id":"911709","name":"KOFAR"},{"id":"9117092010","district_id":"911709","name":"SUMURAMAN"},{"id":"9117092011","district_id":"911709","name":"PANO"},{"id":"9117092012","district_id":"911709","name":"KOGIR"}]